nvme_lint/__init__.py
nvme_lint/__main__.py
nvme_lint/captions.py
nvme_lint/extractor.py
nvme_lint/parser.py
nvme_lint/scheduler.py
nvme_lint/transformer.py
nvme_lint/utils.py
tests/__init__.py
tests/test_extractor.py
tests/test_transformer.py
nvme_lint-0.1.5.dist-info/COPYING
nvme_lint-0.1.5.dist-info/LICENSE
nvme_lint-0.1.5.dist-info/METADATA
nvme_lint-0.1.5.dist-info/WHEEL
nvme_lint-0.1.5.dist-info/entry_points.txt
nvme_lint-0.1.5.dist-info/top_level.txt
nvme_lint-0.1.5.dist-info/RECORD
