Metadata-Version: 2.1
Name: nvme-lint
Version: 0.1.5
Summary: Validate content of NVMe specification
Home-page: https://github.com/linux-nvme/nvme-lint
Author: Karl Bonde Torp
Author-email: k.torp@samsung.com
Classifier: Programming Language :: Python :: 3
Classifier: License :: OSI Approved :: Apache Software License
Classifier: Operating System :: OS Independent
Requires-Python: >=3.6
License-File: LICENSE
License-File: COPYING
Requires-Dist: camelot-py[cv]
Requires-Dist: pyyaml
Requires-Dist: pypdf2 (==2.12.1)
